pyTempPM/__init__.py
pyTempPM/main.py
pyTempPM-0.0.3.dist-info/LICENSE.txt
pyTempPM-0.0.3.dist-info/METADATA
pyTempPM-0.0.3.dist-info/WHEEL
pyTempPM-0.0.3.dist-info/top_level.txt
pyTempPM-0.0.3.dist-info/RECORD
