Metadata-Version: 2.1
Name: pyTempPM
Version: 0.0.3
Summary: A simple python library work with Temp.PM service
Author-email: Nova <info@nova.ws>
License: MIT License
Project-URL: Homepage, https://nova.ws
Project-URL: Repository, https://github.com/novaws/pyTempPM
Keywords: notes,cryptography,private message,self-destroy,self-destruct
Classifier: Programming Language :: Python :: 3.6
Classifier: License :: OSI Approved :: MIT License
Classifier: Operating System :: OS Independent
Requires-Python: >=3.6
License-File: LICENSE.txt
Requires-Dist: requests
Requires-Dist: beautifulsoup4
